life_prolonging-0.0.4.data/scripts/lpl.py
lplib/__init__.py
lplib/choice.py
lplib/meal.py
lplib/store.toml
lplib/util.py
life_prolonging-0.0.4.dist-info/LICENSE
life_prolonging-0.0.4.dist-info/METADATA
life_prolonging-0.0.4.dist-info/WHEEL
life_prolonging-0.0.4.dist-info/entry_points.txt
life_prolonging-0.0.4.dist-info/top_level.txt
life_prolonging-0.0.4.dist-info/RECORD
