Metadata-Version: 2.1
Name: life-prolonging
Version: 0.0.4
Summary: 代码帮你选择
Home-page: https://github.com/deadwind4/life-prolonging
Author: deadwind
Author-email: deadwind4@outlook.com
License: MIT Licence
Keywords: tool,health
Platform: UNKNOWN
Classifier: Programming Language :: Python :: 3
Classifier: License :: OSI Approved :: MIT License
Requires-Dist: toml
